polars_deltalake-0.2.0.dist-info/METADATA
polars_deltalake-0.2.0.dist-info/WHEEL
polars_deltalake/_internal.pyi
polars_deltalake/__init__.py
polars_deltalake/_internal.pyd
polars_deltalake-0.2.0.dist-info/RECORD
